pyadr/__init__.py
pyadr/__version__.py
pyadr/assets/0000-record-architecture-decisions.md
pyadr/assets/0001-use-markdown-architectural-decision-records.md
pyadr/assets/__init__.py
pyadr/assets/madr-template.md
pyadr/cli/__init__.py
pyadr/cli/application.py
pyadr/cli/commands.py
pyadr/cli/config.py
pyadr/cli/io.py
pyadr/config.py
pyadr/const.py
pyadr/content_utils.py
pyadr/core.py
pyadr/exceptions.py
pyadr/file_utils.py
pyadr/git/__init__.py
pyadr/git/cli/__init__.py
pyadr/git/cli/application.py
pyadr/git/cli/commands.py
pyadr/git/config.py
pyadr/git/const.py
pyadr/git/core.py
pyadr/git/exceptions.py
pyadr/git/utils.py
pyadr-0.19.0.dist-info/entry_points.txt
pyadr-0.19.0.dist-info/LICENSE
pyadr-0.19.0.dist-info/WHEEL
pyadr-0.19.0.dist-info/METADATA
pyadr-0.19.0.dist-info/RECORD
